[
  {
    "ContainingType": "ToDoApi.Controllers.TaskController",
    "Method": "GetAll",
    "RelativePath": "api/Task",
    "HttpMethod": "GET",
    "IsController": true,
    "Order": 0,
    "Parameters": [
      {
        "Name": "status",
        "Type": "System.String",
        "IsRequired": false
      },
      {
        "Name": "priority",
        "Type": "System.String",
        "IsRequired": false
      },
      {
        "Name": "sortOrder",
        "Type": "System.String",
        "IsRequired": false
      }
    ],
    "ReturnTypes": [
      {
        "Type": "System.Collections.Generic.IEnumerable\u00601[[ToDoApi.Entity.Task, ToDoApi, Version=1.0.0.0, Culture=neutral, PublicKeyToken=null]]",
        "MediaTypes": [
          "text/plain",
          "application/json",
          "text/json"
        ],
        "StatusCode": 200
      }
    ]
  },
  {
    "ContainingType": "ToDoApi.Controllers.TaskController",
    "Method": "CreateTask",
    "RelativePath": "api/Task",
    "HttpMethod": "POST",
    "IsController": true,
    "Order": 0,
    "Parameters": [
      {
        "Name": "createTaskDto",
        "Type": "ToDoApi.Models.Dtos.CreateTaskDto",
        "IsRequired": true
      }
    ],
    "ReturnTypes": [
      {
        "Type": "ToDoApi.Entity.Task",
        "MediaTypes": [
          "text/plain",
          "application/json",
          "text/json"
        ],
        "StatusCode": 200
      }
    ]
  },
  {
    "ContainingType": "ToDoApi.Controllers.TaskController",
    "Method": "DeleteAllAsync",
    "RelativePath": "api/Task",
    "HttpMethod": "DELETE",
    "IsController": true,
    "Order": 0,
    "Parameters": [],
    "ReturnTypes": []
  },
  {
    "ContainingType": "ToDoApi.Controllers.TaskController",
    "Method": "GetById",
    "RelativePath": "api/Task/{id}",
    "HttpMethod": "GET",
    "IsController": true,
    "Order": 0,
    "Parameters": [
      {
        "Name": "id",
        "Type": "System.Int32",
        "IsRequired": true
      }
    ],
    "ReturnTypes": [
      {
        "Type": "ToDoApi.Entity.Task",
        "MediaTypes": [
          "text/plain",
          "application/json",
          "text/json"
        ],
        "StatusCode": 200
      }
    ]
  },
  {
    "ContainingType": "ToDoApi.Controllers.TaskController",
    "Method": "UpdateAsync",
    "RelativePath": "api/Task/{id}",
    "HttpMethod": "PUT",
    "IsController": true,
    "Order": 0,
    "Parameters": [
      {
        "Name": "id",
        "Type": "System.Int32",
        "IsRequired": true
      },
      {
        "Name": "updateTaskDto",
        "Type": "ToDoApi.Models.Dtos.UpdateTaskDto",
        "IsRequired": true
      }
    ],
    "ReturnTypes": []
  },
  {
    "ContainingType": "ToDoApi.Controllers.TaskController",
    "Method": "DeleteAsync",
    "RelativePath": "api/Task/{id}",
    "HttpMethod": "DELETE",
    "IsController": true,
    "Order": 0,
    "Parameters": [
      {
        "Name": "id",
        "Type": "System.Int32",
        "IsRequired": true
      }
    ],
    "ReturnTypes": []
  }
]